agron_load/__init__.py
agron_load-1.0.3.dist-info/METADATA
agron_load-1.0.3.dist-info/WHEEL
agron_load-1.0.3.dist-info/top_level.txt
agron_load-1.0.3.dist-info/RECORD
