Metadata-Version: 2.1
Name: agron-load
Version: 1.0.3
Summary: Loader module for Agron data collection microservices
Home-page: https://github.com/akhtariali/agron_load
Author: Ali Akhtari
Author-email: hi@aliakh.me
License: UNKNOWN
Platform: UNKNOWN
Classifier: Programming Language :: Python :: 3
Classifier: License :: OSI Approved :: MIT License
Classifier: Operating System :: OS Independent
Requires-Python: >=3.8
Requires-Dist: python-dotenv
Requires-Dist: requests
Requires-Dist: boto3
